MANIFEST.in
README.rst
buildout.cfg
develop.cfg
requirements.txt
setup.py
version.txt
bob/__init__.py
bob.db.lfw.egg-info/PKG-INFO
bob.db.lfw.egg-info/SOURCES.txt
bob.db.lfw.egg-info/dependency_links.txt
bob.db.lfw.egg-info/entry_points.txt
bob.db.lfw.egg-info/not-zip-safe
bob.db.lfw.egg-info/requires.txt
bob.db.lfw.egg-info/top_level.txt
bob/db/__init__.py
bob/db/lfw/__init__.py
bob/db/lfw/create.py
bob/db/lfw/driver.py
bob/db/lfw/models.py
bob/db/lfw/query.py
bob/db/lfw/test.py
doc/conf.py
doc/guide.rst
doc/index.rst
doc/py_api.rst