Metadata-Version: 1.1
Name: bob.db.lfw
Version: 2.1.6
Summary: Labeled Faces in the Wild Database Access API for Bob
Home-page: http://gitlab.idiap.ch/bob/bob.db.lfw
Author: Manuel Guenther
Author-email: manuel.guenther@idiap.ch
License: BSD
Platform: UNKNOWN
Classifier: Framework :: Bob
Classifier: Development Status :: 4 - Beta
Classifier: Intended Audience :: Developers
Classifier: License :: OSI Approved :: BSD License
Classifier: Natural Language :: English
Classifier: Programming Language :: Python
Classifier: Programming Language :: Python :: 3
Classifier: Topic :: Scientific/Engineering :: Artificial Intelligence
Classifier: Topic :: Database :: Front-Ends
